idem_aiohttp/conf.py
idem_aiohttp/version.py
idem_aiohttp/acct/request/basic_auth.py
idem_aiohttp/acct/request/init.py
idem_aiohttp/exec/request/init.py
idem_aiohttp/exec/request/json_request.py
idem_aiohttp/exec/request/raw.py
idem_aiohttp/tool/request/application.py
idem_aiohttp/tool/request/session.py
idem_aiohttp/tool/type/dict.py
idem_aiohttp-3.0.1.dist-info/LICENSE
idem_aiohttp-3.0.1.dist-info/METADATA
idem_aiohttp-3.0.1.dist-info/WHEEL
idem_aiohttp-3.0.1.dist-info/top_level.txt
idem_aiohttp-3.0.1.dist-info/RECORD
