Metadata-Version: 2.1
Name: idem-aiohttp
Version: 3.0.1
Home-page: 
Author: Tyler Johnson
Author-email: tyjohnson@vmware.com
Classifier: Environment :: Console
Classifier: Intended Audience :: Developers
Classifier: Intended Audience :: Information Technology
Classifier: Intended Audience :: System Administrators
Classifier: Operating System :: OS Independent
Classifier: Programming Language :: Python
Classifier: Programming Language :: Python :: 3.8
Classifier: Programming Language :: Python :: 3.9
Classifier: Programming Language :: Python :: 3.10
Classifier: Programming Language :: Python :: 3.11
Classifier: Development Status :: 5 - Production/Stable
Requires-Python: >=3.8
License-File: LICENSE
Requires-Dist: aiohttp[speedups]
Requires-Dist: idem >=17.0.0
Requires-Dist: acct
Requires-Dist: pop >=20.0.0
Requires-Dist: pop-config >=7.0.2
Requires-Dist: rend >=6.3.1
Requires-Dist: pop-loop >=1.0.4
Requires-Dist: PyYaml >=6.0.1
